odoo/addons/partner_exception/README.rst
odoo/addons/partner_exception/__init__.py
odoo/addons/partner_exception/__manifest__.py
odoo/addons/partner_exception/i18n/es.po
odoo/addons/partner_exception/i18n/partner_exception.pot
odoo/addons/partner_exception/models/__init__.py
odoo/addons/partner_exception/models/res_partner.py
odoo/addons/partner_exception/readme/CONTRIBUTORS.rst
odoo/addons/partner_exception/readme/DESCRIPTION.rst
odoo/addons/partner_exception/readme/USAGE.rst
odoo/addons/partner_exception/static/description/icon.png
odoo/addons/partner_exception/static/description/index.html
odoo/addons/partner_exception/views/contact_views.xml
odoo_addon_partner_exception-15.0.1.0.0.6.dist-info/METADATA
odoo_addon_partner_exception-15.0.1.0.0.6.dist-info/WHEEL
odoo_addon_partner_exception-15.0.1.0.0.6.dist-info/top_level.txt
odoo_addon_partner_exception-15.0.1.0.0.6.dist-info/RECORD
